color_contrast/__init__.py
color_contrast/contrast.py
color_contrast-0.1.1.dist-info/METADATA
color_contrast-0.1.1.dist-info/WHEEL
color_contrast-0.1.1.dist-info/RECORD
