Metadata-Version: 2.1
Name: color-contrast
Version: 0.1.1
Summary: Python library to calculate and modulate color contrasts according to WCAG2.1
Home-page: https://github.com/ZugBahnHof/color-contrast
License: BSD-3-Clause
Keywords: color,colour,accessibility,wcag,wcag2.1
Author: Julian Leucker
Author-email: leuckerj@gmail.com
Requires-Python: >=3.10,<4.0
Classifier: License :: OSI Approved :: BSD License
Classifier: Programming Language :: Python :: 3
Classifier: Programming Language :: Python :: 3.10
Classifier: Programming Language :: Python :: 3.11
Classifier: Programming Language :: Python :: 3.12
Requires-Dist: colour (>=0.1.5,<0.2.0)
Project-URL: Repository, https://github.com/ZugBahnHof/color-contrast
